tbert/__init__.py
tbert/attention.py
tbert/bert.py
tbert/data.py
tbert/embedding.py
tbert/gelu.py
tbert/optimization.py
tbert/tf_util.py
tbert/transformer.py
tbert-0.1.8.dist-info/LICENSE
tbert-0.1.8.dist-info/LICENSE-APACHE
tbert-0.1.8.dist-info/METADATA
tbert-0.1.8.dist-info/WHEEL
tbert-0.1.8.dist-info/top_level.txt
tbert-0.1.8.dist-info/RECORD
